{
  "display": {
    "icon": {
      "item": "minecraft:lapis_lazuli"
    },
    "title": {
      "translate": "advancements.runicarts.magicalgems.title"
    },
    "description": {
      "translate": "advancements.runicarts.magicalgems.description"
    },
    "frame": "task",
    "show_toast": true,
    "announce_to_chat": true,
    "hidden": false
  },
  "parent": "runicarts:runicarts",
  "criteria": {
    "requirement": {
      "trigger": "minecraft:inventory_changed",
      "conditions": {
        "items": [
          {
            "items": [
              "minecraft:lapis_lazuli"
            ]
          },
          {
            "items": [
              "minecraft:amethyst_shard"
            ]
          }
        ]
      }
    }
  }
}