{
  "type": "modonomicon:dense",
  "pattern": [
    [
      "___s___",
      "_s___s_",
      "_______",
      "s__0__s",
      "_______",
      "_s___s_",
      "___s___"
    ],
    [
      "___S___",
      "_S___S_",
      "_______",
      "S_____S",
      "_______",
      "_S___S_",
      "___S___"
    ],
    [
      "__SSS__",
      "_S_S_S_",
      "S__S__S",
      "SSSsSSS",
      "S__S__S",
      "_S_S_S_",
      "__SSS__"
    ]
  ],
  "mapping": {
    "s": {
      "type": "modonomicon:block",
      "block": "runology:shattered_block"
    },
    "S": {
      "type": "modonomicon:block",
      "block": "runology:shatterstone"
    },
    "0": {
      "type": "modonomicon:block",
      "block": "runology:shatter"
    }
  }
}